pytest_dparam.py
pytest_dparam-1.0.0.dist-info/LICENSE
pytest_dparam-1.0.0.dist-info/METADATA
pytest_dparam-1.0.0.dist-info/WHEEL
pytest_dparam-1.0.0.dist-info/top_level.txt
pytest_dparam-1.0.0.dist-info/RECORD
