Metadata-Version: 2.1
Name: pytest_dparam
Version: 1.0.0
Summary: A more readable alternative to @pytest.mark.parametrize.
Author-email: Bunker D <contact@bunkerd.fr>
Project-URL: Homepage, https://github.com/Bunker-D/pytest_dparam
Project-URL: Repository, https://github.com/Bunker-D/pytest_dparam
Project-URL: Documentation, https://github.com/Bunker-D/pytest_dparam/blob/main/README.md
Keywords: pytest,tests,testing,parametrize,parametrized
Classifier: Development Status :: 6 - Mature
Classifier: License :: OSI Approved :: MIT License
Classifier: Framework :: Pytest
Classifier: Intended Audience :: Developers
Classifier: Topic :: Software Development :: Testing :: Unit
Classifier: Programming Language :: Python :: 3
License-File: LICENSE
Requires-Dist: pytest
Provides-Extra: dev
Requires-Dist: black-with-tabs ; extra == 'dev'
Requires-Dist: build ; extra == 'dev'
